phfetch/__init__.py
phfetch/core.py
phfetch/query.py
phfetch/utils.py
phfetch-1.1.dist-info/LICENSE
phfetch-1.1.dist-info/METADATA
phfetch-1.1.dist-info/WHEEL
phfetch-1.1.dist-info/top_level.txt
phfetch-1.1.dist-info/RECORD
