Metadata-Version: 2.1
Name: phfetch
Version: 1.1
Summary: A light pornhub downloading interface
Home-page: https://github.com/Egsagon/pornhub-fetch/
Author: Egsagon
Author-email: egsagon12@gmail.com
License: MIT
Platform: unix
Platform: linux
Platform: win32
Platform: cygwin
Classifier: Development Status :: 4 - Beta
Classifier: License :: OSI Approved :: MIT License
Classifier: Programming Language :: Python :: 3.11
Requires-Python: >=3.11
License-File: LICENSE
Requires-Dist: requests (>=2)
